{
  "repoName": "LiveCalc",
  "currentPRD": {
    "id": "PRD-LC-010-REVISED",
    "name": "Modular Orchestration Layer - Engine DAG & SharedArrayBuffer Bus"
  },
  "currentStory": {
    "id": "",
    "title": ""
  },
  "iteration": 2,
  "sessionStartTime": "2026-01-28T05:54:36Z",
  "model": "sonnet",
  "mode": "ALL",
  "status": "running",
  "workQueue": [{"id":"PRD-LC-010-REVISED","name":"Modular Orchestration Layer - Engine DAG & SharedArrayBuffer Bus","pending":3,"total":8},{"id":"PRD-LC-011","name":"Go/No-Go Demo - Proof of Horsepower & Architecture","pending":8,"total":8}],
  "completedThisSession": 1,
  "archive": [{"id":"PRD-LC-001","name":"C++ Projection Engine Core","completedAt":"2026-01-26T08:44:41Z"},{"id":"PRD-LC-001-REVISED","name":"C++ Projection Engine Core - With Python UDF Extensibility","completedAt":"2026-01-27T21:35:44Z"},{"id":"PRD-LC-002","name":"WASM Compilation and Web Worker Threading","completedAt":"2026-01-26T08:44:43Z"},{"id":"PRD-LC-003","name":"VS Code Extension Foundation","completedAt":"2026-01-26T08:44:44Z"},{"id":"PRD-LC-004","name":"Results Panel and Visualisation","completedAt":"2026-01-26T08:44:45Z"},{"id":"PRD-LC-005","name":"Auto-Run and Hot Reload","completedAt":"2026-01-26T08:44:45Z"},{"id":"PRD-LC-006","name":"Assumptions Manager Integration","completedAt":"2026-01-26T08:44:48Z"},{"id":"PRD-LC-006-REFACTOR","name":"Assumptions Manager Integration - Refactored as Shared Library","completedAt":"2026-01-27T22:39:17Z"},{"id":"PRD-LC-007","name":"Python ESG (Economic Scenario Generator) Engine","completedAt":"2026-01-27T23:49:36Z"},{"id":"PRD-LC-008","name":"Python Solver Engine for Parameter Optimization","completedAt":"2026-01-28T00:57:32Z"},{"id":"PRD-LC-010","name":"Modular Orchestration Layer & Shared Data Bus","completedAt":"2026-01-26T08:44:50Z"},{"id":"PRD-LC-012","name":"Cloud Runtime & Execution Bridge","completedAt":"2026-01-26T08:44:51Z"},{"id":"PRD-LC-013","name":"Cloud Platform Management (PaaS Features)","completedAt":"2026-01-26T08:44:53Z"},{"id":"PRD-LC-014","name":"Project Standards & Architecture Documentation","completedAt":"2026-01-26T08:45:05Z"},{"id":"SPIKE-LC-007","name":"Engine Performance Infrastructure: Work-Stealing and SIMD Build","completedAt":"2026-01-26T08:45:06Z"},{"id":"SPIKE-LC-007","name":"Engine Performance Infrastructure: Work-Stealing and SIMD Build","completedAt":"2026-01-26T08:45:06Z"}],
  "testResults": {"totalTests":389,"passed":378,"failed":11,"lastRun":"2026-01-28 05:58:56"},
  "analytics": {"sessions":[{"date":"2026-01-27","time":"20:02","storyId":"US-001","title":"C++ Assumptions Client (PRD-LC-006-REFACTOR)","outcome":"COMPLETE"},{"date":"2026-01-27","time":"20:45","storyId":"US-001","title":"Policy Data Structure (PRD-LC-001-REVISED)","outcome":"COMPLETE"},{"date":"2026-01-27","time":"21:15","storyId":"US-002","title":"Assumption Tables & Resolution (PRD-LC-001-REVISED)","outcome":"COMPLETE"},{"date":"2026-01-27","time":"21:30","storyId":"US-003","title":"Economic Scenario Structure (PRD-LC-001-REVISED)","outcome":"COMPLETE"},{"date":"2026-01-27","time":"21:45","storyId":"US-004","title":"Single Policy Projection with UDF Integration (PRD-LC-001-REVISED)","outcome":"COMPLETE"},{"date":"2026-01-27","time":"20:05","storyId":"US-005","title":"Nested Stochastic Valuation (PRD-LC-001-REVISED)","outcome":"COMPLETE"},{"date":"2026-01-27","time":"21:25","storyId":"US-006","title":"Command Line Interface (PRD-LC-001-REVISED)","outcome":"COMPLETE"},{"date":"2026-01-27","time":"21:35","storyId":"US-008","title":"Data Format: Parquet Input/Output (PRD-LC-001-REVISED)","outcome":"COMPLETE"},{"date":"2026-01-27","time":"22:10","storyId":"US-002","title":"Python Assumptions Client (PRD-LC-006-REFACTOR)","outcome":"COMPLETE"},{"date":"2026-01-27","time":"22:45","storyId":"US-003","title":"JWT Token Management (PRD-LC-006-REFACTOR)","outcome":"COMPLETE"}],"aggregate":{"today":9,"thisWeek":32,"thisMonth":32,"totalStories":32,"modelUsage":{},"healingEvents":0}},
  "lastUpdate": "2026-01-28T05:59:07Z"
}
